gateau_desktop/__init__.py
gateau_desktop/__main__.py
gateau_desktop/constants.py
gateau_desktop/emulator_listener.py
gateau_desktop/environment.py
gateau_desktop/gateau_client.py
gateau_desktop/ram_monitor.py
gateau_desktop-0.1.1.dist-info/WHEEL
gateau_desktop-0.1.1.dist-info/METADATA
gateau_desktop-0.1.1.dist-info/RECORD
