Metadata-Version: 2.1
Name: gateau-desktop
Version: 0.1.1
Summary: 
Author: Kevin Duff
Author-email: kevinkelduff@gmail.com
Requires-Python: >=3.8,<4.0
Classifier: Programming Language :: Python :: 3
Classifier: Programming Language :: Python :: 3.10
Classifier: Programming Language :: Python :: 3.8
Classifier: Programming Language :: Python :: 3.9
Requires-Dist: aiohttp (>=3.8.1,<4.0.0)
Requires-Dist: click (>=8.0.4,<9.0.0)
Requires-Dist: firebasil (>=0.1.6,<0.2.0)
Requires-Dist: pydantic (>=1.9.0,<2.0.0)
Requires-Dist: requests (>=2.27.1,<3.0.0)
